{"status": "REQUEST_SUCCEEDED", "responseTime": 201, "message": [], "Results": {"series": [{"seriesID": "JTU000000270000000JOL", "data": [{"year": "2021", "period": "M12", "periodName": "December", "value": "213", "footnotes": [{}]}, {"year": "2021", "period": "M11", "periodName": "November", "value": "188", "footnotes": [{}]}, {"year": "2021", "period": "M10", "periodName": "October", "value": "259", "footnotes": [{}]}, {"year": "2021", "period": "M09", "periodName": "September", "value": "203", "footnotes": [{}]}, {"year": "2021", "period": "M08", "periodName": "August", "value": "189", "footnotes": [{}]}, {"year": "2021", "period": "M07", "periodName": "July", "value": "214", "footnotes": [{}]}, {"year": "2021", "period": "M06", "periodName": "June", "value": "179", "footnotes": [{}]}, {"year": "2021", "period": "M05", "periodName": "May", "value": "193", "footnotes": [{}]}, {"year": "2021", "period": "M04", "periodName": "April", "value": "184", "footnotes": [{}]}, {"year": "2021", "period": "M03", "periodName": "March", "value": "125", "footnotes": [{}]}, {"year": "2021", "period": "M02", "periodName": "February", "value": "127", "footnotes": [{}]}, {"year": "2021", "period": "M01", "periodName": "January", "value": "119", "footnotes": [{}]}, {"year": "2020", "period": "M12", "periodName": "December", "value": "102", "footnotes": [{}]}, {"year": "2020", "period": "M11", "periodName": "November", "value": "116", "footnotes": [{}]}, {"year": "2020", "period": "M10", "periodName": "October", "value": "134", "footnotes": [{}]}, {"year": "2020", "period": "M09", "periodName": "September", "value": "111", "footnotes": [{}]}, {"year": "2020", "period": "M08", "periodName": "August", "value": "113", "footnotes": [{}]}, {"year": "2020", "period": "M07", "periodName": "July", "value": "140", "footnotes": [{}]}, {"year": "2020", "period": "M06", "periodName": "June", "value": "98", "footnotes": [{}]}, {"year": "2020", "period": "M05", "periodName": "May", "value": "90", "footnotes": [{}]}, {"year": "2020", "period": "M04", "periodName": "April", "value": "103", "footnotes": [{}]}, {"year": "2020", "period": "M03", "periodName": "March", "value": "106", "footnotes": [{}]}, {"year": "2020", "period": "M02", "periodName": "February", "value": "114", "footnotes": [{}]}, {"year": "2020", "period": "M01", "periodName": "January", "value": "131", "footnotes": [{}]}, {"year": "2019", "period": "M12", "periodName": "December", "value": "112", "footnotes": [{}]}, {"year": "2019", "period": "M11", "periodName": "November", "value": "121", "footnotes": [{}]}, {"year": "2019", "period": "M10", "periodName": "October", "value": "127", "footnotes": [{}]}, {"year": "2019", "period": "M09", "periodName": "September", "value": "134", "footnotes": [{}]}, {"year": "2019", "period": "M08", "periodName": "August", "value": "141", "footnotes": [{}]}, {"year": "2019", "period": "M07", "periodName": "July", "value": "143", "footnotes": [{}]}, {"year": "2019", "period": "M06", "periodName": "June", "value": "144", "footnotes": [{}]}, {"year": "2019", "period": "M05", "periodName": "May", "value": "166", "footnotes": [{}]}, {"year": "2019", "period": "M04", "periodName": "April", "value": "162", "footnotes": [{}]}, {"year": "2019", "period": "M03", "periodName": "March", "value": "135", "footnotes": [{}]}, {"year": "2019", "period": "M02", "periodName": "February", "value": "140", "footnotes": [{}]}, {"year": "2019", "period": "M01", "periodName": "January", "value": "149", "footnotes": [{}]}]}]}}