{"status": "REQUEST_SUCCEEDED", "responseTime": 316, "message": [], "Results": {"series": [{"seriesID": "JTU000000400000000JOL", "data": [{"year": "2021", "period": "M12", "periodName": "December", "value": "112", "footnotes": [{}]}, {"year": "2021", "period": "M11", "periodName": "November", "value": "106", "footnotes": [{}]}, {"year": "2021", "period": "M10", "periodName": "October", "value": "133", "footnotes": [{}]}, {"year": "2021", "period": "M09", "periodName": "September", "value": "129", "footnotes": [{}]}, {"year": "2021", "period": "M08", "periodName": "August", "value": "104", "footnotes": [{}]}, {"year": "2021", "period": "M07", "periodName": "July", "value": "128", "footnotes": [{}]}, {"year": "2021", "period": "M06", "periodName": "June", "value": "112", "footnotes": [{}]}, {"year": "2021", "period": "M05", "periodName": "May", "value": "103", "footnotes": [{}]}, {"year": "2021", "period": "M04", "periodName": "April", "value": "120", "footnotes": [{}]}, {"year": "2021", "period": "M03", "periodName": "March", "value": "107", "footnotes": [{}]}, {"year": "2021", "period": "M02", "periodName": "February", "value": "89", "footnotes": [{}]}, {"year": "2021", "period": "M01", "periodName": "January", "value": "92", "footnotes": [{}]}, {"year": "2020", "period": "M12", "periodName": "December", "value": "77", "footnotes": [{}]}, {"year": "2020", "period": "M11", "periodName": "November", "value": "75", "footnotes": [{}]}, {"year": "2020", "period": "M10", "periodName": "October", "value": "92", "footnotes": [{}]}, {"year": "2020", "period": "M09", "periodName": "September", "value": "79", "footnotes": [{}]}, {"year": "2020", "period": "M08", "periodName": "August", "value": "89", "footnotes": [{}]}, {"year": "2020", "period": "M07", "periodName": "July", "value": "94", "footnotes": [{}]}, {"year": "2020", "period": "M06", "periodName": "June", "value": "76", "footnotes": [{}]}, {"year": "2020", "period": "M05", "periodName": "May", "value": "79", "footnotes": [{}]}, {"year": "2020", "period": "M04", "periodName": "April", "value": "86", "footnotes": [{}]}, {"year": "2020", "period": "M03", "periodName": "March", "value": "72", "footnotes": [{}]}, {"year": "2020", "period": "M02", "periodName": "February", "value": "75", "footnotes": [{}]}, {"year": "2020", "period": "M01", "periodName": "January", "value": "85", "footnotes": [{}]}, {"year": "2019", "period": "M12", "periodName": "December", "value": "65", "footnotes": [{}]}, {"year": "2019", "period": "M11", "periodName": "November", "value": "67", "footnotes": [{}]}, {"year": "2019", "period": "M10", "periodName": "October", "value": "92", "footnotes": [{}]}, {"year": "2019", "period": "M09", "periodName": "September", "value": "87", "footnotes": [{}]}, {"year": "2019", "period": "M08", "periodName": "August", "value": "85", "footnotes": [{}]}, {"year": "2019", "period": "M07", "periodName": "July", "value": "85", "footnotes": [{}]}, {"year": "2019", "period": "M06", "periodName": "June", "value": "81", "footnotes": [{}]}, {"year": "2019", "period": "M05", "periodName": "May", "value": "91", "footnotes": [{}]}, {"year": "2019", "period": "M04", "periodName": "April", "value": "86", "footnotes": [{}]}, {"year": "2019", "period": "M03", "periodName": "March", "value": "87", "footnotes": [{}]}, {"year": "2019", "period": "M02", "periodName": "February", "value": "71", "footnotes": [{}]}, {"year": "2019", "period": "M01", "periodName": "January", "value": "79", "footnotes": [{}]}]}]}}